dirmapper/__init__.py
dirmapper/config.py
dirmapper/main.py
dirmapper/formatter/__init__.py
dirmapper/formatter/formatter.py
dirmapper/generator/__init__.py
dirmapper/generator/directory_structure_generator.py
dirmapper/generator/reader.py
dirmapper/ignore/__init__.py
dirmapper/ignore/ignore_list_reader.py
dirmapper/ignore/path_ignorer.py
dirmapper/styles/__init__.py
dirmapper/styles/base_style.py
dirmapper/styles/flat_list_style.py
dirmapper/styles/html_style.py
dirmapper/styles/indentation_style.py
dirmapper/styles/json_style.py
dirmapper/styles/markdown_style.py
dirmapper/styles/tree_style.py
dirmapper/utils/__init__.py
dirmapper/utils/cli_utils.py
dirmapper/utils/logger.py
dirmapper/utils/sorting_strategy.py
dirmapper/writer/__init__.py
dirmapper/writer/structure_writer.py
dirmapper/writer/template_parser.py
dirmapper/writer/writer.py
dirmapper-1.0.7.dist-info/LICENSE
dirmapper-1.0.7.dist-info/METADATA
dirmapper-1.0.7.dist-info/WHEEL
dirmapper-1.0.7.dist-info/entry_points.txt
dirmapper-1.0.7.dist-info/top_level.txt
dirmapper-1.0.7.dist-info/RECORD
