Metadata-Version: 2.1
Name: dirmapper
Version: 1.0.7
Summary: A CLI tool to generate a directory structure mapping.
Author-email: Nash Dean <nashdean.github@gmail.com>
License: MIT
Project-URL: homepage, https://github.com/nashdean/dirmap
Requires-Python: >=3.9
License-File: LICENSE
Provides-Extra: dev
Requires-Dist: pytest; extra == "dev"
